modulardqn/DQN.py
modulardqn/__init__.py
modulardqn/dqnmain.py
modulardqn/core/NoisyLinear.py
modulardqn/core/QNetwork.py
modulardqn/core/__init__.py
modulardqn/core/models.py
modulardqn/core/replaymemory.py
modulardqn/core/sumtree.py
modulardqn/logging/__init__.py
modulardqn/logging/cli.py
modulardqn/logging/episodelog.py
modulardqn/logging/logger.py
modulardqn/logging/wandblogger.py
modulardqn/scripts/__init__.py
modulardqn/scripts/eval_model.py
modulardqn/scripts/heatmap.py
modulardqn/scripts/main.py
modulardqn/utils/__init__.py
modulardqn/utils/cliparser.py
modulardqn/utils/configfile.py
modulardqn/utils/loss_funcs.py
modulardqn/utils/optimizers.py
modulardqn/utils/plotter.py
modulardqn/utils/simulation.py
modulardqn/utils/sweep.py
modulardqn/wrappers/__init__.py
modulardqn/wrappers/frameskipping.py
modulardqn/wrappers/imagepreprocessing.py
modulardqn/wrappers/recordstatistics.py
modulardqn/wrappers/rewardclipping.py
modulardqn-1.0.0.dist-info/LICENSE
modulardqn-1.0.0.dist-info/METADATA
modulardqn-1.0.0.dist-info/WHEEL
modulardqn-1.0.0.dist-info/entry_points.txt
modulardqn-1.0.0.dist-info/top_level.txt
modulardqn-1.0.0.dist-info/RECORD
