Metadata-Version: 2.1
Name: modulardqn
Version: 1.0.0
Summary: An implementation of the DQN algorithm and all improvments of rainbow DQN
Author-email: Laurenz Levi Spielmann <laurenz-levi.spielmann@tu-dortmund.de>, Julian Bohnenkämper <julian.bohnenkaemper@tu-dortmund.de>, Pascal Makossa <pascal.makossa@tu-dortmund.de>
License: MIT License
Requires-Python: >=3.8
License-File: LICENSE
Requires-Dist: torch
Requires-Dist: prettytable
Requires-Dist: gymnasium
Requires-Dist: opencv-python
